{
  "className": "ContractFriendly",
  "type": "OBJECT",
  "descr": "\"A formal agreement between parties regarding the conduct of business, exchange of information or other matters.\"",
  "parent": "BackboneElement",
  "isInnerClass": true,
  "autoIncrement": true,
  "fields": [
    {
      "name": "contentAttachment",
      "descr": "\"Human readable rendering of this Contract in a format and representation intended to enhance comprehension and ensure understandability.\"",
      "typeName": "Attachment",
      "isArray": false,
      "isRequired": false,
      "size": 1024,
      "isTransient": false,
      "type": "COMPLEX",
      "entityType": "PRIMITIVE",
      "entityTypeName": "string",
      "autoGenerated": false
    },
    {
      "name": "contentReference",
      "descr": "\"Human readable rendering of this Contract in a format and representation intended to enhance comprehension and ensure understandability.\"",
      "typeName": "Reference",
      "isArray": false,
      "isRequired": false,
      "size": 1024,
      "isTransient": false,
      "type": "OBJECT",
      "entityType": "OBJECTARRAY",
      "entityTypeName": "Reference",
      "autoGenerated": false
    }
  ],
  "searches": []
}