{
  "className": "ProcedureRequestRequester",
  "type": "OBJECT",
  "descr": "\"A record of a request for diagnostic investigations, treatments, or operations to be performed.\"",
  "parent": "BackboneElement",
  "isInnerClass": true,
  "autoIncrement": false,
  "fields": [
    {
      "name": "agent",
      "descr": "\"The device, practitioner or organization who initiated the request.\"",
      "typeName": "Reference",
      "isArray": false,
      "isRequired": true,
      "size": 1024,
      "isTransient": false,
      "type": "OBJECT",
      "entityType": "OBJECTARRAY",
      "entityTypeName": "Reference",
      "autoGenerated": false
    },
    {
      "name": "onBehalfOf",
      "descr": "\"The organization the device or practitioner was acting on behalf of.\"",
      "typeName": "Reference",
      "isArray": false,
      "isRequired": false,
      "size": 1024,
      "isTransient": false,
      "type": "OBJECT",
      "entityType": "OBJECTARRAY",
      "entityTypeName": "Reference",
      "autoGenerated": false
    }
  ],
  "searches": []
}